homework_1.srcs/sources_1/new/out_none.v
`timescale 1ns / 1ps
//////////////////////////////////////////////////////////////////////////////////
// Company: 
// Engineer: 
// 
// Create Date: 2026/09/23 15:40:10
// Design Name: 
// Module Name: out_none
// Project Name: 
// Target Devices: 
// Tool Versions: 
// Description: 
// 
// Dependencies: 
// 
// Revision:
// Revision 0.01 - File Created
// Additional Comments:
// 
//////////////////////////////////////////////////////////////////////////////////


module out_none(    //根据选位选择输出结果
    input [3:0] pos,    //选位信号
    input [6:0] seled_seg,  //译码后结果
    input CE,   //开关信号
    output reg [6:0] seg    //最终输出给7段显示管的结果
    );

    always @(*) begin
        if(!CE) seg = 7'b0111111;   //开关对开显示管显示一个横杠
        else begin
        case(pos)   //如果选择第一位则输出译码后结果，如果选择其他位就输出一个横杠的显示
            4'b1110: seg = seled_seg;
            default: seg = 7'b0111111;
        endcase 
        end
    end

endmodule

homework_1.srcs/sources_1/new/scan.v
`timescale 1ns / 1ps
//////////////////////////////////////////////////////////////////////////////////
// Company: 
// Engineer: 
// 
// Create Date: 2026/09/23 15:08:59
// Design Name: 
// Module Name: scan
// Project Name: 
// Target Devices: 
// Tool Versions: 
// Description: 
// 
// Dependencies: 
// 
// Revision:
// Revision 0.01 - File Created
// Additional Comments:
// 
//////////////////////////////////////////////////////////////////////////////////


module scan #(
    parameter COUNT_CLK = 10_000
)
    (    //选位扫描，clk为100MHz，刷新率为250Hz
    input clk,
    input rst,
    output reg [3:0] pos
    );

    reg [13:0] count;//计数器

    always @(posedge clk) begin
        if(rst) begin   //复位信号，按下count置零，pos选位至第一位
            count <= 14'd0;
            pos <= 4'b1110;
        end
        else if(count == COUNT_CLK) begin //count计数10_000，pos信号循环左移，每秒左移1_000次，刷新率即为250Hz
            pos <= {pos[2:0],pos[3]};
            count <= 14'd0;
        end
        else begin
            count <= count + 1; //计数
        end
    end
endmodule

homework_1.srcs/sim_1/new/scan_out_tb.v
`timescale 1ns/1ps
module scan_out_tb ;    //扫描及选位输出测试
    reg clk;
    reg rst;
    reg [6:0] seled_seg;
    reg CE;
    wire [3:0] pos;
    wire [6:0] seg;

    scan #(
        .COUNT_CLK(1)
    ) u1 (.clk(clk),
    .rst(rst),
    .pos(pos));

    out_none u2 (.pos(pos),
    .seled_seg(seled_seg),
    .CE(CE),
    .seg(seg));
    
    initial begin
        clk = 1'b0;
    end
    always #5 clk = ~clk;

    initial begin
        $dumpfile("scan_out_tb.vcd");
        $dumpvars(0,scan_out_tb);

        rst = 1'b0;
        seled_seg = 7'b0101001;
        CE = 1'b1;      //初始化，假设一个译码结果

        #20;      
        rst = 1'b1;     //复位信号测试

        #20;
        rst = 1'b0;

        #20;
        CE = 1'b0;  //开关信号测试

        #20;
        CE = 1'b1;

        #60;//在上述测试的同时，选位会左移，同时可以观察是否正确移位
        $finish;

    end

    initial begin
        $monitor("time=%0t clk=%d rst=%d seled_seg=%d CE=%d pos=%d seg=%d",
        $time,clk,rst,seled_seg,CE,pos,seg);
    end

endmodule

homework_1.sim/sim_1/behav/xsim/scan_out_tb.vcd
$date
   Wed Sep 30 16:58:09 2026
$end
$version
  2019.1
$end
$timescale
  1ps
$end
$scope module scan_out_tb $end
$var reg 1 ! clk $end
$var reg 1 " rst $end
$var reg 7 # seled_seg [6:0] $end
$var reg 1 $ CE $end
$var wire 4 % pos [3:0] $end
$var wire 7 & seg [6:0] $end
$scope module u1 $end
$var wire 1 ' clk $end
$var wire 1 ( rst $end
$var reg 4 ) pos [3:0] $end
$var reg 14 * count [13:0] $end
$var parameter 32 + COUNT_CLK [31:0] $end
$upscope $end
$scope module u2 $end
$var wire 4 % pos [3:0] $end
$var wire 7 , seled_seg [6:0] $end
$var wire 1 - CE $end
$var reg 7 . seg [6:0] $end
$upscope $end
$upscope $end
$enddefinitions $end
#0
$dumpvars
0!
0"
b101001 #
1$
bx %
b111111 &
0'
0(
bx )
bx *
b1 +
b101001 ,
1-
b111111 .
$end
#5000
1!
1'
#10000
0!
0'
#15000
1!
1'
#20000
0!
1"
0'
1(
#25000
1!
b1110 %
b101001 &
1'
b1110 )
b0 *
b101001 .
#30000
0!
0'
#35000
1!
1'
#40000
0!
0"
0'
0(
#45000
1!
1'
b1 *
#50000
0!
0'
#55000
1!
b1101 %
b111111 &
1'
b1101 )
b0 *
b111111 .
#60000
0!
0$
0'
0-
b111111 .
#65000
1!
1'
b1 *
#70000
0!
0'
#75000
1!
b1011 %
1'
b1011 )
b0 *
b111111 .
#80000
0!
1$
0'
1-
b111111 .
#85000
1!
1'
b1 *
#90000
0!
0'
#95000
1!
b111 %
1'
b111 )
b0 *
b111111 .
#100000
0!
0'
#105000
1!
1'
b1 *
#110000
0!
0'
#115000
1!
b1110 %
b101001 &
1'
b1110 )
b0 *
b101001 .
#120000
0!
0'
#125000
1!
1'
b1 *
#130000
0!
0'
#135000
1!
b1101 %
b111111 &
1'
b1101 )
b0 *
b111111 .
