homework_1.srcs/sources_1/new/method_assign.v
`timescale 1ns / 1ps
//////////////////////////////////////////////////////////////////////////////////
// Company: 
// Engineer: 
// 
// Create Date: 2026/09/23 11:40:04
// Design Name: 
// Module Name: method_assign
// Project Name: 
// Target Devices: 
// Tool Versions: 
// Description: 
// 
// Dependencies: 
// 
// Revision:
// Revision 0.01 - File Created
// Additional Comments:
// 
//////////////////////////////////////////////////////////////////////////////////


module method_assign(//数据流
    input [1:0] bin,//输入二进制数
    input EN,//使能信号
    output wire [6:0] seg
    );

    assign seg[0] = (~bin[1])&bin[0] | (~EN);
    assign seg[1] = 1'b0;
    assign seg[2] = bin[1]&(~bin[0])&EN;
    assign seg[3] = (~bin[1])&bin[0] | (~EN);
    assign seg[4] = bin[0] | (~EN) ;
    assign seg[5] = (bin[1]&EN) | (bin[0]&EN) ;
    assign seg[6] = (~bin[1])&EN ;
endmodule

homework_1.srcs/sources_1/new/method_behavior.v
`timescale 1ns / 1ps
//////////////////////////////////////////////////////////////////////////////////
// Company: 
// Engineer: 
// 
// Create Date: 2026/09/23 11:40:04
// Design Name: 
// Module Name: method_behavior
// Project Name: 
// Target Devices: 
// Tool Versions: 
// Description: 
// 
// Dependencies: 
// 
// Revision:
// Revision 0.01 - File Created
// Additional Comments:
// 
//////////////////////////////////////////////////////////////////////////////////


module method_behavior(
    input [1:0] bin,
    input EN,
    output reg [6:0] seg
    );

    always @(*) begin
        if(!EN) seg = 7'b0011001; //使能端为0，七段译码器输出显示4
        else begin
            case(bin)   //使能端为1，输入数据译码
            4'b00: seg = 7'b1000000;
            4'b01: seg = 7'b1111001;
            4'b10: seg = 7'b0100100;
            4'b11: seg = 7'b0110000;
            default: seg = 7'b1111111;
            endcase
            end
        end
endmodule

homework_1.srcs/sources_1/new/method_struct.v
`timescale 1ns / 1ps
//////////////////////////////////////////////////////////////////////////////////
// Company: 
// Engineer: 
// 
// Create Date: 2026/09/23 11:40:04
// Design Name: 
// Module Name: method_struct
// Project Name: 
// Target Devices: 
// Tool Versions: 
// Description: 
// 
// Dependencies: 
// 
// Revision:
// Revision 0.01 - File Created
// Additional Comments:
// 
//////////////////////////////////////////////////////////////////////////////////


module method_struct(   //结构化
    input [1:0] bin,
    input EN,
    output wire [6:0] seg
    );
    
    wire bn_1,//bin[1]非
    bn_0,//bin[0]非
    EN_n,//EN非
    b_and,//bin[0]&bin[1]
    bn1_b0_and,//(~bin[1])&bin[0]
    b1_EN_and,//bin[1]&EN
    b0_EN_and;//bin[0]&EN

    not(bn_1,bin[1]);
    not(bn_0,bin[0]);
    not(EN_n,EN);
    and(b_and,bin[0],bin[1]);
    and(bn1_b0_and,bn_1,bin[0]);
    and(b1_EN_and,bin[1],EN);
    and(b0_EN_and,bin[0],EN);

    or(seg[0],bn1_b0_and,EN_n);
    or(seg[1],1'd0,1'd0);
    and(seg[2],bin[1],bn_0,EN);
    or(seg[3],bn1_b0_and,EN_n);
    or(seg[4],bin[0],EN_n);
    or(seg[5],b1_EN_and,b0_EN_and);
    and(seg[6],bn_1,EN);
    
    
endmodule

homework_1.srcs/sources_1/new/module_select.v
`timescale 1ns / 1ps
//////////////////////////////////////////////////////////////////////////////////
// Company: 
// Engineer: 
// 
// Create Date: 2026/09/23 11:40:04
// Design Name: 
// Module Name: module_select
// Project Name: 
// Target Devices: 
// Tool Versions: 
// Description: 
// 
// Dependencies: 
// 
// Revision:
// Revision 0.01 - File Created
// Additional Comments:
// 
//////////////////////////////////////////////////////////////////////////////////


module module_select(   //译码并在三个方法里选择
    input [1:0] sel,
    input EN,
    input [1:0] D,
    output reg [6:0] sel_seg
    );

    wire [6:0] a_seg;
    wire [6:0] b_seg;
    wire [6:0] s_seg;

    method_struct u1 ( //结构化方法译码
        .bin(D),
        .EN(EN),
        .seg(s_seg)
    );

    method_behavior u2 (    //行为级描述译码
        .bin(D),
        .EN(EN),
        .seg(b_seg)
    );

    method_assign u3 (  //数据流描述译码
        .bin(D),
        .EN(EN),
        .seg(a_seg)
    );

    always @(*) begin
        case(sel)
            2'd0: sel_seg = a_seg;//数据流
            2'd1: sel_seg = b_seg;//行为
            2'd2: sel_seg = s_seg;//结构化
            default: sel_seg = s_seg;//默认用结构化描述
        endcase
    end

endmodule

homework_1.srcs/sim_1/new/sel_method_tb.v
`timescale 1ns / 1ps
module sel_method_tb;   //三种译码结果及选择测试
    reg [1:0] sel;
    reg EN;
    reg [1:0] D;
    wire [6:0] sel_seg;
    integer i;

    module_select u1 (
        .sel(sel),
        .EN(EN),
        .D(D),
        .sel_seg(sel_seg)
    );

    initial begin
        $dumpfile("sel_method_tb.vcd");
        $dumpvars(0,sel_method_tb);

        EN = 1'b1;
        sel = 2'b00;
        D = 2'b00;
        i = 0;

        for(i = 0; i < 4; i = i +1) begin   //遍历四种选择，在每种选择下，查看不同数据输入的译码正确性
            #20;
            D = 2'b01;

            #20;
            D = 2'b10;

            #20;
            D = 2'b11;      //遍历数据输入

            #20;
            EN = 1'b0;      //使能端测试

            #20;
            D = 2'b00;

            #20;
            EN = 1'b1;

            #20;
            sel = sel + 1;

        end

        #20;
        $finish;
    end

    initial begin
        $monitor("time%0t sel=%d EN=%d D=%d sel_seg=%d",
        $time,sel,EN,D,sel_seg);
    end


endmodule

homework_1.sim/sim_1/behav/xsim/sel_method_tb.vcd
$date
   Thu Oct  1 14:22:09 2026
$end
$version
  2019.1
$end
$timescale
  1ps
$end
$scope module sel_method_tb $end
$var reg 2 ! sel [1:0] $end
$var reg 1 " EN $end
$var reg 2 # D [1:0] $end
$var wire 7 $ sel_seg [6:0] $end
$var integer 32 % i $end
$scope module u1 $end
$var wire 2 & sel [1:0] $end
$var wire 1 ' EN $end
$var wire 2 ( D [1:0] $end
$var reg 7 ) sel_seg [6:0] $end
$var wire 7 * a_seg [6:0] $end
$var wire 7 + b_seg [6:0] $end
$var wire 7 , s_seg [6:0] $end
$scope module u1 $end
$var wire 2 ( bin [1:0] $end
$var wire 1 ' EN $end
$var wire 7 , seg [6:0] $end
$var wire 1 - bn_1 $end
$var wire 1 . bn_0 $end
$var wire 1 / EN_n $end
$var wire 1 0 b_and $end
$var wire 1 1 bn1_b0_and $end
$var wire 1 2 b1_EN_and $end
$var wire 1 3 b0_EN_and $end
$upscope $end
$scope module u2 $end
$var wire 2 ( bin [1:0] $end
$var wire 1 ' EN $end
$var reg 7 4 seg [6:0] $end
$upscope $end
$scope module u3 $end
$var wire 2 ( bin [1:0] $end
$var wire 1 ' EN $end
$var wire 7 * seg [6:0] $end
$upscope $end
$upscope $end
$upscope $end
$enddefinitions $end
#0
$dumpvars
b0 !
1"
b0 #
b1000000 $
b0 %
b0 &
1'
b0 (
b1000000 )
b1000000 *
b1000000 +
b1000000 ,
1-
1.
0/
00
01
02
03
b1000000 4
$end
#20000
b1 #
b1111001 $
b1 (
b1111001 )
b1111001 *
b1111001 +
b1111001 ,
0.
11
13
b1111001 4
#40000
b10 #
b100100 $
b10 (
b100100 )
b100100 *
b100100 +
b100100 ,
0-
1.
01
12
03
b100100 4
#60000
b11 #
b110000 $
b11 (
b110000 )
b110000 *
b110000 +
b110000 ,
0.
10
01
13
b110000 4
#80000
0"
b11001 $
0'
b11001 )
b11001 *
b11001 +
b11001 ,
1/
02
03
b11001 4
#100000
b0 #
b0 (
b11001 *
b11001 ,
1-
1.
00
01
02
03
b11001 4
#120000
1"
b1000000 $
1'
b1000000 )
b1000000 *
b1000000 +
b1000000 ,
0/
02
03
b1000000 4
#140000
b1 !
b1 %
b1 &
b1000000 )
#160000
b1 #
b1111001 $
b1 (
b1111001 )
b1111001 *
b1111001 +
b1111001 ,
0.
11
13
b1111001 4
#180000
b10 #
b100100 $
b10 (
b100100 )
b100100 *
b100100 +
b100100 ,
0-
1.
01
12
03
b100100 4
#200000
b11 #
b110000 $
b11 (
b110000 )
b110000 *
b110000 +
b110000 ,
0.
10
01
13
b110000 4
#220000
0"
b11001 $
0'
b11001 )
b11001 *
b11001 +
b11001 ,
1/
02
03
b11001 4
#240000
b0 #
b0 (
b11001 *
b11001 ,
1-
1.
00
01
02
03
b11001 4
#260000
1"
b1000000 $
1'
b1000000 )
b1000000 *
b1000000 +
b1000000 ,
0/
02
03
b1000000 4
#280000
b10 !
b10 %
b10 &
b1000000 )
#300000
b1 #
b1111001 $
b1 (
b1111001 )
b1111001 *
b1111001 +
b1111001 ,
0.
11
13
b1111001 4
#320000
b10 #
b100100 $
b10 (
b100100 )
b100100 *
b100100 +
b100100 ,
0-
1.
01
12
03
b100100 4
#340000
b11 #
b110000 $
b11 (
b110000 )
b110000 *
b110000 +
b110000 ,
0.
10
01
13
b110000 4
#360000
0"
b11001 $
0'
b11001 )
b11001 *
b11001 +
b11001 ,
1/
02
03
b11001 4
#380000
b0 #
b0 (
b11001 *
b11001 ,
1-
1.
00
01
02
03
b11001 4
#400000
1"
b1000000 $
1'
b1000000 )
b1000000 *
b1000000 +
b1000000 ,
0/
02
03
b1000000 4
#420000
b11 !
b11 %
b11 &
b1000000 )
#440000
b1 #
b1111001 $
b1 (
b1111001 )
b1111001 *
b1111001 +
b1111001 ,
0.
11
13
b1111001 4
#460000
b10 #
b100100 $
b10 (
b100100 )
b100100 *
b100100 +
b100100 ,
0-
1.
01
12
03
b100100 4
#480000
b11 #
b110000 $
b11 (
b110000 )
b110000 *
b110000 +
b110000 ,
0.
10
01
13
b110000 4
#500000
0"
b11001 $
0'
b11001 )
b11001 *
b11001 +
b11001 ,
1/
02
03
b11001 4
#520000
b0 #
b0 (
b11001 *
b11001 ,
1-
1.
00
01
02
03
b11001 4
#540000
1"
b1000000 $
1'
b1000000 )
b1000000 *
b1000000 +
b1000000 ,
0/
02
03
b1000000 4
#560000
b0 !
b100 %
b0 &
b1000000 )
